distsrserver/__init__.py
distsrserver-0.0.0.dist-info/METADATA
distsrserver-0.0.0.dist-info/WHEEL
distsrserver-0.0.0.dist-info/licenses/LICENSE
distsrserver-0.0.0.dist-info/RECORD
